vayu/__init__.py
vayu/aio.py
vayu/cache.py
vayu/common.py
vayu/lock.py
vayu/log.py
vayu/pandas_utils.py
vayu/parallel.py
vayu/plotly_utils.py
vayu/statistics.py
vayu/time.py
vayulib-0.1.0.dist-info/METADATA
vayulib-0.1.0.dist-info/WHEEL
vayulib-0.1.0.dist-info/RECORD
