Metadata-Version: 2.3
Name: vayulib
Version: 0.1.0
Summary: 
License: MIT
Author: Alok Tripathy
Author-email: developer@alok.one
Requires-Python: >=3.12,<4.0
Classifier: License :: OSI Approved :: MIT License
Classifier: Programming Language :: Python :: 3
Classifier: Programming Language :: Python :: 3.12
Classifier: Programming Language :: Python :: 3.13
Provides-Extra: data
Requires-Dist: aiohttp (>=3.11.13,<4.0.0)
Requires-Dist: numpy (>=2.1.3,<3.0.0) ; extra == "data"
Requires-Dist: pandas (>=2.2.3,<3.0.0) ; extra == "data"
Requires-Dist: plotly (>=6.0.0,<7.0.0) ; extra == "data"
Requires-Dist: pytest (>=8.3.5,<9.0.0)
